Metadata-Version: 2.2
Name: scikits-odes-core
Version: 3.1.1
Summary: Core support module for scikits-odes
Author-email: "B. Malengier" <benny.malengier@gmail.org>
Maintainer-email: "B. Malengier" <benny.malengier@gmail.org>
License: # Copyright (C) 2011-12  Pavol Kišon
Project-URL: Homepage, http://cage.ugent.be/~bm/progs.html
Project-URL: Documentation, https://scikits-odes.readthedocs.io/en/stable/
Project-URL: Repository, https://github.com/bmcage/odes
Project-URL: Issues, https://github.com/bmcage/odes/issues
Project-URL: Paper, https://doi.org/10.21105/joss.00165
Project-URL: DOI, https://doi.org/10.5281/zenodo.5511691
Classifier: Development Status :: 5 - Production/Stable
Classifier: Environment :: Console
Classifier: Intended Audience :: Developers
Classifier: Intended Audience :: Science/Research
Classifier: License :: OSI Approved :: BSD License
Classifier: Topic :: Scientific/Engineering
Classifier: Programming Language :: Python :: 3
Classifier: Programming Language :: Python :: 3 :: Only
Classifier: Programming Language :: Python :: 3.7
Classifier: Programming Language :: Python :: 3.8
Classifier: Programming Language :: Python :: 3.9
Classifier: Programming Language :: Python :: 3.10
Classifier: Programming Language :: Python :: 3.11
License-File: LICENSE.txt
